{
  "records": [
    {
      "company": "Global Payments",
      "symbol": "GPN",
      "date": "2026-02-18",
      "bmo_amc": "TBD",
      "nasdaq_time_label": "time-not-supplied",
      "yahoo_time_label": null,
      "source": "aggregator",
      "sector": "Finance"
    },
    {
      "company": "Moody's Corporation",
      "symbol": "MCO",
      "date": "2026-02-18",
      "bmo_amc": "TBD",
      "nasdaq_time_label": "time-not-supplied",
      "yahoo_time_label": null,
      "source": "aggregator",
      "sector": "Finance"
    },
    {
      "company": "Caesars Entertainment Inc",
      "symbol": "CZR",
      "date": "2026-02-17",
      "bmo_amc": "TIME-AFTER-HOURS",
      "nasdaq_time_label": "time-after-hours",
      "yahoo_time_label": null,
      "source": "aggregator",
      "sector": "Manufacturing"
    },
    {
      "company": "Leidos Holdings Inc",
      "symbol": "LDOS",
      "date": "2026-02-17",
      "bmo_amc": "TIME-PRE-MARKET",
      "nasdaq_time_label": "time-pre-market",
      "yahoo_time_label": null,
      "source": "aggregator",
      "sector": "Manufacturing"
    },
    {
      "company": "Republic Services Inc",
      "symbol": "RSG",
      "date": "2026-02-17",
      "bmo_amc": "TIME-AFTER-HOURS",
      "nasdaq_time_label": "time-after-hours",
      "yahoo_time_label": null,
      "source": "aggregator",
      "sector": "Manufacturing"
    },
    {
      "company": "Vulcan Materials Co",
      "symbol": "VMC",
      "date": "2026-02-17",
      "bmo_amc": "TIME-PRE-MARKET",
      "nasdaq_time_label": "time-pre-market",
      "yahoo_time_label": null,
      "source": "aggregator",
      "sector": "Manufacturing"
    },
    {
      "company": "American Water Works",
      "symbol": "AWK",
      "date": "2026-02-18",
      "bmo_amc": "TBD",
      "nasdaq_time_label": "time-not-supplied",
      "yahoo_time_label": null,
      "source": "aggregator",
      "sector": "Manufacturing"
    },
    {
      "company": "Booking Holdings Inc",
      "symbol": "BKNG",
      "date": "2026-02-18",
      "bmo_amc": "TBD",
      "nasdaq_time_label": "time-not-supplied",
      "yahoo_time_label": null,
      "source": "aggregator",
      "sector": "Manufacturing"
    },
    {
      "company": "Host Hotels & Resorts Inc",
      "symbol": "HST",
      "date": "2026-02-18",
      "bmo_amc": "TBD",
      "nasdaq_time_label": "time-not-supplied",
      "yahoo_time_label": null,
      "source": "aggregator",
      "sector": "Manufacturing"
    },
    {
      "company": "Invitation Homes Inc",
      "symbol": "INVH",
      "date": "2026-02-18",
      "bmo_amc": "TBD",
      "nasdaq_time_label": "time-not-supplied",
      "yahoo_time_label": null,
      "source": "aggregator",
      "sector": "Manufacturing"
    },
    {
      "company": "Nordson Corp",
      "symbol": "NDSN",
      "date": "2026-02-18",
      "bmo_amc": "TBD",
      "nasdaq_time_label": "time-not-supplied",
      "yahoo_time_label": null,
      "source": "aggregator",
      "sector": "Manufacturing"
    },
    {
      "company": "Celanese",
      "symbol": "CE",
      "date": "2026-02-17",
      "bmo_amc": "TIME-AFTER-HOURS",
      "nasdaq_time_label": "time-after-hours",
      "yahoo_time_label": null,
      "source": "aggregator",
      "sector": "Resources"
    },
    {
      "company": "Constellation Energy",
      "symbol": "CEG",
      "date": "2026-02-17",
      "bmo_amc": "TBD",
      "nasdaq_time_label": "time-not-supplied",
      "yahoo_time_label": null,
      "source": "aggregator",
      "sector": "Resources"
    },
    {
      "company": "DTE",
      "symbol": "DTE",
      "date": "2026-02-17",
      "bmo_amc": "TIME-PRE-MARKET",
      "nasdaq_time_label": "time-pre-market",
      "yahoo_time_label": null,
      "source": "aggregator",
      "sector": "Resources"
    },
    {
      "company": "Devon Energy",
      "symbol": "DVN",
      "date": "2026-02-17",
      "bmo_amc": "TIME-AFTER-HOURS",
      "nasdaq_time_label": "time-after-hours",
      "yahoo_time_label": null,
      "source": "aggregator",
      "sector": "Resources"
    },
    {
      "company": "EQT Corp",
      "symbol": "EQT",
      "date": "2026-02-17",
      "bmo_amc": "TIME-AFTER-HOURS",
      "nasdaq_time_label": "time-after-hours",
      "yahoo_time_label": null,
      "source": "aggregator",
      "sector": "Resources"
    },
    {
      "company": "Energy Transfer",
      "symbol": "ET",
      "date": "2026-02-17",
      "bmo_amc": "TIME-PRE-MARKET",
      "nasdaq_time_label": "time-pre-market",
      "yahoo_time_label": null,
      "source": "aggregator",
      "sector": "Resources"
    },
    {
      "company": "Expand Energy",
      "symbol": "EXE",
      "date": "2026-02-17",
      "bmo_amc": "TIME-AFTER-HOURS",
      "nasdaq_time_label": "time-after-hours",
      "yahoo_time_label": null,
      "source": "aggregator",
      "sector": "Resources"
    },
    {
      "company": "First Energy",
      "symbol": "FE",
      "date": "2026-02-17",
      "bmo_amc": "TIME-AFTER-HOURS",
      "nasdaq_time_label": "time-after-hours",
      "yahoo_time_label": null,
      "source": "aggregator",
      "sector": "Resources"
    },
    {
      "company": "CF Industries",
      "symbol": "CF",
      "date": "2026-02-18",
      "bmo_amc": "TBD",
      "nasdaq_time_label": "time-not-supplied",
      "yahoo_time_label": null,
      "source": "aggregator",
      "sector": "Resources"
    },
    {
      "company": "Edison International",
      "symbol": "EIX",
      "date": "2026-02-18",
      "bmo_amc": "TBD",
      "nasdaq_time_label": "time-not-supplied",
      "yahoo_time_label": null,
      "source": "aggregator",
      "sector": "Resources"
    },
    {
      "company": "HF Sinclair",
      "symbol": "DINO",
      "date": "2026-02-18",
      "bmo_amc": "TBD",
      "nasdaq_time_label": "time-not-supplied",
      "yahoo_time_label": null,
      "source": "aggregator",
      "sector": "Resources"
    },
    {
      "company": "Nutrien",
      "symbol": "NTR",
      "date": "2026-02-18",
      "bmo_amc": "TBD",
      "nasdaq_time_label": "time-not-supplied",
      "yahoo_time_label": null,
      "source": "aggregator",
      "sector": "Resources"
    },
    {
      "company": "Occidental Petroleum",
      "symbol": "OXY",
      "date": "2026-02-18",
      "bmo_amc": "TBD",
      "nasdaq_time_label": "time-not-supplied",
      "yahoo_time_label": null,
      "source": "aggregator",
      "sector": "Resources"
    },
    {
      "company": "Texas Pacific Land",
      "symbol": "TPL",
      "date": "2026-02-18",
      "bmo_amc": "TBD",
      "nasdaq_time_label": "time-not-supplied",
      "yahoo_time_label": null,
      "source": "aggregator",
      "sector": "Resources"
    },
    {
      "company": "PPL Corp",
      "symbol": "PPL",
      "date": "2026-02-20",
      "bmo_amc": "TBD",
      "nasdaq_time_label": "time-not-supplied",
      "yahoo_time_label": null,
      "source": "aggregator",
      "sector": "Resources"
    },
    {
      "company": "Kenvue",
      "symbol": "KVUE",
      "date": "2026-02-17",
      "bmo_amc": "TIME-AFTER-HOURS",
      "nasdaq_time_label": "time-after-hours",
      "yahoo_time_label": null,
      "source": "aggregator",
      "sector": "Pharma"
    },
    {
      "company": "Labcorp Holdings Inc",
      "symbol": "LH",
      "date": "2026-02-17",
      "bmo_amc": "TIME-PRE-MARKET",
      "nasdaq_time_label": "time-pre-market",
      "yahoo_time_label": null,
      "source": "aggregator",
      "sector": "Pharma"
    },
    {
      "company": "Medtronic PLC",
      "symbol": "MDT",
      "date": "2026-02-17",
      "bmo_amc": "TIME-PRE-MARKET",
      "nasdaq_time_label": "time-pre-market",
      "yahoo_time_label": null,
      "source": "aggregator",
      "sector": "Pharma"
    },
    {
      "company": "Charles River Labs",
      "symbol": "CRL",
      "date": "2026-02-18",
      "bmo_amc": "TBD",
      "nasdaq_time_label": "time-not-supplied",
      "yahoo_time_label": null,
      "source": "aggregator",
      "sector": "Pharma"
    },
    {
      "company": "Insulet",
      "symbol": "PODD",
      "date": "2026-02-18",
      "bmo_amc": "TBD",
      "nasdaq_time_label": "time-not-supplied",
      "yahoo_time_label": null,
      "source": "aggregator",
      "sector": "Pharma"
    },
    {
      "company": "Coca-Cola Europacific",
      "symbol": "CCEP",
      "date": "2026-02-17",
      "bmo_amc": "TIME-PRE-MARKET",
      "nasdaq_time_label": "time-pre-market",
      "yahoo_time_label": null,
      "source": "aggregator",
      "sector": "Consumer"
    },
    {
      "company": "DoorDash",
      "symbol": "DASH",
      "date": "2026-02-18",
      "bmo_amc": "TBD",
      "nasdaq_time_label": "time-not-supplied",
      "yahoo_time_label": null,
      "source": "aggregator",
      "sector": "Consumer"
    },
    {
      "company": "Molson Coors Beverage Co",
      "symbol": "TAP",
      "date": "2026-02-18",
      "bmo_amc": "TBD",
      "nasdaq_time_label": "time-not-supplied",
      "yahoo_time_label": null,
      "source": "aggregator",
      "sector": "Consumer"
    },
    {
      "company": "Cadence",
      "symbol": "CDNS",
      "date": "2026-02-17",
      "bmo_amc": "TIME-AFTER-HOURS",
      "nasdaq_time_label": "time-after-hours",
      "yahoo_time_label": null,
      "source": "aggregator",
      "sector": "TMT"
    },
    {
      "company": "Palo Alto",
      "symbol": "PANW",
      "date": "2026-02-17",
      "bmo_amc": "TIME-AFTER-HOURS",
      "nasdaq_time_label": "time-after-hours",
      "yahoo_time_label": null,
      "source": "aggregator",
      "sector": "TMT"
    },
    {
      "company": "Analog Devices",
      "symbol": "ADI",
      "date": "2026-02-18",
      "bmo_amc": "TBD",
      "nasdaq_time_label": "time-not-supplied",
      "yahoo_time_label": null,
      "source": "aggregator",
      "sector": "TMT"
    },
    {
      "company": "Figma",
      "symbol": "FIG",
      "date": "2026-02-18",
      "bmo_amc": "TBD",
      "nasdaq_time_label": "time-not-supplied",
      "yahoo_time_label": null,
      "source": "aggregator",
      "sector": "TMT"
    },
    {
      "company": "Garmin",
      "symbol": "GRMN",
      "date": "2026-02-18",
      "bmo_amc": "TBD",
      "nasdaq_time_label": "time-not-supplied",
      "yahoo_time_label": null,
      "source": "aggregator",
      "sector": "TMT"
    },
    {
      "company": "Omnicom",
      "symbol": "OMC",
      "date": "2026-02-18",
      "bmo_amc": "TBD",
      "nasdaq_time_label": "time-not-supplied",
      "yahoo_time_label": null,
      "source": "aggregator",
      "sector": "TMT"
    },
    {
      "company": "eBay",
      "symbol": "EBAY",
      "date": "2026-02-18",
      "bmo_amc": "TBD",
      "nasdaq_time_label": "time-not-supplied",
      "yahoo_time_label": null,
      "source": "aggregator",
      "sector": "TMT"
    }
  ],
  "count": 41,
  "missingPublic": [
    "CDPQ",
    "CPPIB"
  ],
  "tickerCount": 568,
  "generatedAt": "2026-04-23T07:22:35Z",
  "irCompanies": [],
  "fallbackCompanies": [
    "American Water Works",
    "Analog Devices",
    "Booking Holdings Inc",
    "CF Industries",
    "Cadence",
    "Caesars Entertainment Inc",
    "Celanese",
    "Charles River Labs",
    "Coca-Cola Europacific",
    "Constellation Energy",
    "DTE",
    "Devon Energy",
    "DoorDash",
    "EQT Corp",
    "Edison International",
    "Energy Transfer",
    "Expand Energy",
    "Figma",
    "First Energy",
    "Garmin",
    "Global Payments",
    "HF Sinclair",
    "Host Hotels & Resorts Inc",
    "Insulet",
    "Invitation Homes Inc",
    "Kenvue",
    "Labcorp Holdings Inc",
    "Leidos Holdings Inc",
    "Medtronic PLC",
    "Molson Coors Beverage Co",
    "Moody's Corporation",
    "Nordson Corp",
    "Nutrien",
    "Occidental Petroleum",
    "Omnicom",
    "PPL Corp",
    "Palo Alto",
    "Republic Services Inc",
    "Texas Pacific Land",
    "Vulcan Materials Co",
    "eBay"
  ],
  "week": {
    "id": "2026-02-16",
    "start_date": "2026-02-16",
    "end_date": "2026-02-20",
    "label": "Week of Feb 16 to Feb 20"
  },
  "sector": "All sectors",
  "sectorSlug": "all",
  "downloadPath": "downloads/2026-02-16/earnings_all_2026-02-16.csv"
}