{
  "records": [
    {
      "company": "Lennar Corp",
      "symbol": "LEN",
      "date": "2026-03-12",
      "bmo_amc": "TIME-AFTER-HOURS",
      "nasdaq_time_label": "time-after-hours",
      "yahoo_time_label": null,
      "source": "aggregator",
      "sector": "Manufacturing"
    },
    {
      "company": "Lennar Corp",
      "symbol": "LEN",
      "date": "2026-03-13",
      "bmo_amc": "TBD",
      "nasdaq_time_label": null,
      "yahoo_time_label": null,
      "ir_time_label": null,
      "ir_source_url": "https://investors.lennar.com/",
      "source": "investor_relations",
      "sector": "Manufacturing"
    },
    {
      "company": "New Fortress Energy",
      "symbol": "NFE",
      "date": "2026-03-09",
      "bmo_amc": "TBD",
      "nasdaq_time_label": "time-not-supplied",
      "yahoo_time_label": null,
      "source": "aggregator",
      "sector": "Resources"
    },
    {
      "company": "AT&T",
      "symbol": "T",
      "date": "2026-03-09",
      "bmo_amc": "11:35 AM\n                    ET",
      "nasdaq_time_label": null,
      "yahoo_time_label": null,
      "ir_time_label": "11:35 AM\n                    ET",
      "ir_source_url": "https://investors.att.com/news-and-events/events-and-presentations",
      "source": "investor_relations",
      "sector": "TMT"
    },
    {
      "company": "Fox Corp",
      "symbol": "FOXA",
      "date": "2026-03-09",
      "bmo_amc": "8:55 AM EDT",
      "nasdaq_time_label": null,
      "yahoo_time_label": null,
      "ir_time_label": "8:55 AM EDT",
      "ir_source_url": "https://investor.foxcorporation.com/",
      "source": "investor_relations",
      "sector": "TMT"
    },
    {
      "company": "HPE",
      "symbol": "HPE",
      "date": "2026-03-09",
      "bmo_amc": "TIME-AFTER-HOURS",
      "nasdaq_time_label": "time-after-hours",
      "yahoo_time_label": null,
      "ir_time_label": null,
      "ir_source_url": "https://investors.hpe.com/",
      "source": "investor_relations",
      "sector": "TMT"
    },
    {
      "company": "Juniper Networks",
      "symbol": "JNPR",
      "date": "2026-03-09",
      "bmo_amc": "TBD",
      "nasdaq_time_label": null,
      "yahoo_time_label": null,
      "ir_time_label": null,
      "ir_source_url": "https://investors.hpe.com:443/",
      "source": "investor_relations",
      "sector": "TMT"
    },
    {
      "company": "Oracle",
      "symbol": "ORCL",
      "date": "2026-03-10",
      "bmo_amc": "TIME-AFTER-HOURS",
      "nasdaq_time_label": "time-after-hours",
      "yahoo_time_label": null,
      "source": "aggregator",
      "sector": "TMT"
    },
    {
      "company": "Bumble",
      "symbol": "BMBL",
      "date": "2026-03-11",
      "bmo_amc": "TIME-AFTER-HOURS",
      "nasdaq_time_label": "time-after-hours",
      "yahoo_time_label": null,
      "source": "aggregator",
      "sector": "TMT"
    },
    {
      "company": "Shopify",
      "symbol": "SHOP",
      "date": "2026-03-11",
      "bmo_amc": "TBD",
      "nasdaq_time_label": null,
      "yahoo_time_label": null,
      "ir_time_label": null,
      "ir_source_url": "https://www.shopify.com/investors",
      "source": "investor_relations",
      "sector": "TMT"
    },
    {
      "company": "Teradyne",
      "symbol": "TER",
      "date": "2026-03-11",
      "bmo_amc": "4:30 PM EST",
      "nasdaq_time_label": null,
      "yahoo_time_label": null,
      "ir_time_label": "4:30 pm EST",
      "ir_source_url": "https://investors.teradyne.com/",
      "source": "investor_relations",
      "sector": "TMT"
    },
    {
      "company": "Adobe",
      "symbol": "ADBE",
      "date": "2026-03-12",
      "bmo_amc": "TIME-AFTER-HOURS",
      "nasdaq_time_label": "time-after-hours",
      "yahoo_time_label": null,
      "source": "aggregator",
      "sector": "TMT"
    },
    {
      "company": "Alibaba",
      "symbol": "BABA",
      "date": "2026-03-12",
      "bmo_amc": "TBD",
      "nasdaq_time_label": "time-not-supplied",
      "yahoo_time_label": null,
      "source": "aggregator",
      "sector": "TMT"
    },
    {
      "company": "KLA Corp",
      "symbol": "KLAC",
      "date": "2026-03-12",
      "bmo_amc": "9:00 AM EST",
      "nasdaq_time_label": null,
      "yahoo_time_label": null,
      "ir_time_label": "9:00 am EST",
      "ir_source_url": "https://ir.kla.com/",
      "source": "investor_relations",
      "sector": "TMT"
    },
    {
      "company": "SentinelOne",
      "symbol": "S",
      "date": "2026-03-12",
      "bmo_amc": "TIME-AFTER-HOURS",
      "nasdaq_time_label": "time-after-hours",
      "yahoo_time_label": null,
      "source": "aggregator",
      "sector": "TMT"
    },
    {
      "company": "Bank of America",
      "symbol": "BAC",
      "date": "2026-03-10",
      "bmo_amc": "1:20 PM ET",
      "nasdaq_time_label": null,
      "yahoo_time_label": null,
      "ir_time_label": "1:20 pm ET",
      "ir_source_url": "https://investor.bankofamerica.com/",
      "source": "investor_relations",
      "sector": "Finance"
    },
    {
      "company": "Citigroup",
      "symbol": "C",
      "date": "2026-03-10",
      "bmo_amc": "TBD",
      "nasdaq_time_label": null,
      "yahoo_time_label": null,
      "ir_time_label": null,
      "ir_source_url": "https://www.citigroup.com/global/investors",
      "source": "investor_relations",
      "sector": "Finance"
    },
    {
      "company": "Citizens Financial",
      "symbol": "CFG",
      "date": "2026-03-10",
      "bmo_amc": "11:20 AM EST",
      "nasdaq_time_label": null,
      "yahoo_time_label": null,
      "ir_time_label": "11:20 am EST",
      "ir_source_url": "https://investor.citizensbank.com/about-us/investor-relations.aspx",
      "source": "investor_relations",
      "sector": "Finance"
    },
    {
      "company": "PNC Financial",
      "symbol": "PNC",
      "date": "2026-03-10",
      "bmo_amc": "10:40 AM EST",
      "nasdaq_time_label": null,
      "yahoo_time_label": null,
      "ir_time_label": "10:40 am EST",
      "ir_source_url": "https://investor.pnc.com/",
      "source": "investor_relations",
      "sector": "Finance"
    },
    {
      "company": "Coca-Cola Co",
      "symbol": "KO",
      "date": "2026-03-09",
      "bmo_amc": "8:00 AM ET",
      "nasdaq_time_label": null,
      "yahoo_time_label": null,
      "ir_time_label": "8:00 am ET",
      "ir_source_url": "https://investors.coca-colacompany.com/",
      "source": "investor_relations",
      "sector": "Consumer"
    },
    {
      "company": "Campbell Soup Co",
      "symbol": "CPB",
      "date": "2026-03-11",
      "bmo_amc": "TIME-PRE-MARKET",
      "nasdaq_time_label": "time-pre-market",
      "yahoo_time_label": null,
      "source": "aggregator",
      "sector": "Consumer"
    },
    {
      "company": "Dollar General",
      "symbol": "DG",
      "date": "2026-03-12",
      "bmo_amc": "TIME-PRE-MARKET",
      "nasdaq_time_label": "time-pre-market",
      "yahoo_time_label": null,
      "source": "aggregator",
      "sector": "Consumer"
    },
    {
      "company": "Ulta Beauty",
      "symbol": "ULTA",
      "date": "2026-03-12",
      "bmo_amc": "4:30 PM ET",
      "nasdaq_time_label": "time-after-hours",
      "yahoo_time_label": null,
      "ir_time_label": "4:30 pm ET",
      "ir_source_url": "https://www.ulta.com/investor",
      "source": "investor_relations",
      "sector": "Consumer"
    },
    {
      "company": "Becton Dickinson and Co",
      "symbol": "BDX",
      "date": "2026-03-10",
      "bmo_amc": "8:30 AM EST",
      "nasdaq_time_label": null,
      "yahoo_time_label": null,
      "ir_time_label": "8:30 am EST",
      "ir_source_url": "https://investors.bd.com/",
      "source": "investor_relations",
      "sector": "Pharma"
    },
    {
      "company": "Medtronic PLC",
      "symbol": "MDT",
      "date": "2026-03-10",
      "bmo_amc": "10:30 A.M. EST",
      "nasdaq_time_label": null,
      "yahoo_time_label": null,
      "ir_time_label": "10:30 a.m. EST",
      "ir_source_url": "https://investorrelations.medtronic.com/",
      "source": "investor_relations",
      "sector": "Pharma"
    }
  ],
  "count": 25,
  "missingPublic": [
    "CDPQ",
    "CPPIB"
  ],
  "tickerCount": 568,
  "generatedAt": "2026-03-07T01:02:42Z",
  "irCompanies": [
    "AT&T",
    "Bank of America",
    "Becton Dickinson and Co",
    "Citigroup",
    "Citizens Financial",
    "Coca-Cola Co",
    "Fox Corp",
    "HPE",
    "Juniper Networks",
    "KLA Corp",
    "Lennar Corp",
    "Medtronic PLC",
    "PNC Financial",
    "Shopify",
    "Teradyne",
    "Ulta Beauty"
  ],
  "fallbackCompanies": [
    "Adobe",
    "Alibaba",
    "Bumble",
    "Campbell Soup Co",
    "Dollar General",
    "Lennar Corp",
    "New Fortress Energy",
    "Oracle",
    "SentinelOne"
  ],
  "week": {
    "id": "2026-03-09",
    "start_date": "2026-03-09",
    "end_date": "2026-03-13",
    "label": "Week of Mar 9 to Mar 13"
  },
  "sector": "All sectors",
  "sectorSlug": "all",
  "downloadPath": "downloads/2026-03-09/earnings_all_2026-03-09.csv"
}